[
  {
    "id": "167424f8-ca7f-4224-a00b-a54a5a7766c7",
    "CARDINAL": [
      "138",
      "three",
      "nine",
      "27.1",
      "20",
      "100",
      "2020",
      "eight",
      "6",
      "504090",
      "30",
      "9",
      "One",
      "five",
      "12",
      "146",
      "one",
      "six",
      "seven",
      "33",
      "5",
      "10",
      "38,387",
      "two",
      "four",
      "one half",
      "19.5",
      "50.4",
      "11",
      "181",
      "25.68"
    ],
    "ORG": [
      "O'Neal",
      "Russel",
      "MJ",
      "NBA Finals",
      "All-NBA First Team",
      "the Dream Team",
      "NBA",
      "the Orlando Magic",
      "Spurs",
      "Lakers",
      "Russel Westbrook",
      "Ervin",
      "Bulls",
      "the Chicago Bulls' dynasty",
      "the Houston Rockets",
      "Washington Wizards",
      "the Miami Heat",
      "Olajuwon",
      "UCLA",
      "the Boston Celtics",
      "ESPN",
      "Basketball"
    ],
    "DATE": [
      "1995",
      "1994",
      "13 seasons",
      "the decade",
      "the 80s and 90s",
      "Sunday",
      "1968",
      "17 seasons",
      "January of this year",
      "17440",
      "his years",
      "the first five months",
      "this day",
      "1962",
      "almost every year",
      "a single season",
      "their formidable years",
      "age 40",
      "1990",
      "13 years",
      "the 1980s",
      "an eight year span",
      "1961-62",
      "a year",
      "the 90s",
      "2006",
      "the regular season"
    ],
    "FAC": [
      "Kobe Bryant"
    ],
    "PERSON": [
      "Jordan",
      "Wilt Chamberlain's",
      "Chamberlain",
      "Scottie Pippen",
      "Johnson",
      "Bill Russel",
      "Kareem Abdul Jabar",
      "Muhammad Ali",
      "LeBon James",
      "James",
      "Kobe Bryant",
      "Larry Bird",
      "Shaq",
      "Shaquille O'Neal",
      "LeBron",
      "Robert Horry",
      "Bryant",
      "Robertson",
      "The Black Mamba",
      "John Wooden",
      "Kareem Abdul-Jabbar",
      "Larry Legend",
      "Babe Ruth",
      "Michael Jordan",
      "LeBron James",
      "Hakeem Olajuwon",
      "Celtics",
      "Magic Johnson",
      "Bird",
      "Wilt Chamberlain",
      "Oscar Robertson"
    ],
    "WORK_OF_ART": [
      "The \"Big O",
      "The Last Dance",
      "The Dream"
    ],
    "LOC": [
      "the Mount Rushmore"
    ],
    "ORDINAL": [
      "second",
      "first",
      "third",
      "sixth",
      "fourth"
    ],
    "GPE": [
      "Los Angeles",
      "Lew Alcindor",
      "Jordan",
      "Rockets",
      "Bryant",
      "Chicago"
    ],
    "NORP": [
      "Nigerian",
      "Hakeem"
    ],
    "PERCENT": [
      "90%",
      "Birdshot 50%",
      "33%",
      "50%",
      "40%"
    ],
    "QUANTITY": [
      "11.2 apg",
      "7.4 apg"
    ],
    "PRODUCT": [
      "All-NBA"
    ],
    "MONEY": [
      "7.4 rpg",
      "25.7 rpg"
    ]
  },
  {
    "id": "7185ebf3-fa27-4fdc-a9fd-2011165a8603",
    "ORDINAL": [
      "100th"
    ],
    "ORG": [
      "Maine East High School",
      "Des Plaines American Legion Post",
      "Des Plaines American Legion's",
      "Post"
    ],
    "CARDINAL": [
      "247",
      "36"
    ],
    "DATE": [
      "March 21, 2021",
      "about a week ago",
      "1933",
      "Friday, May 29",
      "Aug. 1",
      "1968",
      "52 years ago"
    ],
    "PERSON": [
      "Park Ridge",
      "Tom Strossner"
    ],
    "FAC": [
      "the Edward Hotel",
      "Mannheim Road",
      "the Park Ridge"
    ],
    "GPE": [
      "Chicago",
      "Rosemont"
    ],
    "EVENT": [
      "World's Fair"
    ]
  },
  {
    "id": "16601478-ebd3-4b55-bd54-e292865696e1",
    "GPE": [
      "Longview",
      "Gregg County",
      "U.S.",
      "Abbott",
      "Texas"
    ],
    "MONEY": [
      "963,000",
      "almost $5 million",
      "$1.29 billion",
      "$81.7 million",
      "$2.09 million",
      "262,000",
      "about $392 million"
    ],
    "DATE": [
      "prior years",
      "June",
      "March",
      "the school year",
      "Thursday",
      "this week",
      "March 13",
      "future years",
      "this summer"
    ],
    "ORG": [
      "Houston ISD",
      "School",
      "Spring Hill ISD",
      "Morath",
      "State",
      "Texas Education",
      "TEA"
    ],
    "PERSON": [
      "Chromebooks",
      "Wi-Fi",
      "Betsy DeVos",
      "Greg Abbott",
      "Pine Tree ISD",
      "DeVos",
      "Mike Morath"
    ],
    "PERCENT": [
      "up to 75%",
      "90%",
      "5%"
    ]
  },
  {
    "id": "a6f63029-6c69-49ea-a0dc-a5c7e85f55fb",
    "CARDINAL": [
      "6,000",
      "\\-",
      "21",
      "215",
      "five",
      "13",
      "one",
      "three",
      "245",
      "seven",
      "100",
      "2,200",
      "two",
      "eight"
    ],
    "ORG": [
      "Cyclones",
      "the Tour de France",
      "NBA",
      "the Padres' Chris Paddack",
      "The Last Dance",
      "Reds",
      "NFL",
      "ISU",
      "Davenport Assumption",
      "Yankees",
      "Cubs",
      "Hilton (Coliseum"
    ],
    "GPE": [
      "Strasburg",
      "Utah",
      "Mexico",
      "Iowa",
      "Yanda",
      "Salt Lake City",
      "Peloton",
      "Puerto Vallarta"
    ],
    "PERSON": [
      "Jordan",
      "Karl Malone",
      "Dennis Rodman",
      "Luis Castillo",
      "Kyle Hendricks",
      "Chris Doyle",
      "Marshal Yanda",
      "Sloan",
      "Tommy Kahnle",
      "Pro Bowls",
      "Phil Jackson",
      "Alan Faneca",
      "Dresser",
      "Broderson",
      "Jerry Sloan",
      "Hendricks",
      "Castillo",
      "Julien Broderson",
      "Isiah Thomas",
      "Stephen Strasburg",
      "Michael Jordan",
      "Kahnle",
      "Jerry Krause",
      "Kevin Dresser"
    ],
    "DATE": [
      "early 1970s",
      "January",
      "daily",
      "23 years",
      "last season",
      "the late 1960s",
      "Friday",
      "last week",
      "2010",
      "10 seasons",
      "the age of 78"
    ],
    "FAC": [
      "the Baltimore Ravens"
    ],
    "QUANTITY": [
      "320 pounds",
      "86.7 mph",
      "184 pounds",
      "312 pounds"
    ],
    "TIME": [
      "late-night",
      "at least 45 minutes"
    ],
    "EVENT": [
      "the Chicago Bulls dynasty of 1990s",
      "a Super Bowl"
    ],
    "ORDINAL": [
      "seventh"
    ]
  },
  {
    "id": "70ebe48c-a75d-4236-9ed6-4af0d8e1a421",
    "ORG": [
      "EPCC Board Trustee",
      "EL PASO",
      "University Medical Center",
      "KTSM"
    ],
    "GPE": [
      "El Paso",
      "Soria",
      "Texas"
    ],
    "PERSON": [
      "Bonnie",
      "Leo",
      "Bonnie Soria Najera",
      "Leo Soria's",
      "Soria",
      "Rosie Soria"
    ],
    "DATE": [
      "Memorial Day weekend",
      "Just two days later",
      "two days earlier this month",
      "Tuesday",
      "Sunday",
      "Friday",
      "64",
      "May 15",
      "days",
      "Just a week ago"
    ],
    "CARDINAL": [
      "911",
      "one"
    ],
    "LOC": [
      "Providence East"
    ],
    "TIME": [
      "Just hours",
      "afternoon"
    ]
  },
  {
    "id": "172ac60b-3611-4684-9c75-612abe362a84",
    "CARDINAL": [
      "\\-",
      "10",
      "two"
    ],
    "DATE": [
      "last month",
      "April",
      "December 2019",
      "three days"
    ],
    "GPE": [
      "Sullivan County",
      "Greeneville",
      "Johnson City's",
      "U.S.",
      "D.D.",
      "Johnson City"
    ],
    "ORG": [
      "Johnson City Transit",
      "the Kingsport Times News",
      "District Court"
    ],
    "MONEY": [
      "900,000",
      "$1.2 million",
      "300,000"
    ],
    "NORP": [
      "American",
      "Caucasian",
      "African-American"
    ],
    "PERSON": [
      "E.D.",
      "D.D.",
      "David",
      "Eldona Janutolo"
    ],
    "TIME": [
      "about five minutes",
      "10 minutes",
      "about 10 minutes later"
    ]
  },
  {
    "id": "92123e9a-a03a-48f1-9f57-59319648b9a0",
    "DATE": [
      "2018",
      "1966",
      "last Wednesday",
      "Nov. 6, 2018",
      "many years",
      "years ago",
      "more than a year and a half"
    ],
    "GPE": [
      "Vermont",
      "Montpelier",
      "U.S.",
      "Vietnam"
    ],
    "PERSON": [
      "Lyndon Johnson",
      "George Aiken",
      "Michael Sherman",
      "Montpelier",
      "Bashara"
    ],
    "ORG": [
      "the Montpelier City Council",
      "Aiken",
      "the Vermont Supreme Court"
    ],
    "CARDINAL": [
      "2,459",
      "1,877"
    ],
    "QUANTITY": [
      "27 feet"
    ],
    "NORP": [
      "Hallelujah"
    ]
  },
  {
    "id": "a1433e93-fa9b-4f17-baaa-c64750ef109d",
    "GPE": [
      "Vermont"
    ],
    "MONEY": [
      "about $3.5 million",
      "about $117,000",
      "$1.25 billion"
    ],
    "LAW": [
      "CARES Act"
    ],
    "CARDINAL": [
      "approximately 2,000",
      "One"
    ],
    "DATE": [
      "June 30",
      "just two months ago",
      "years",
      "the middle of March",
      "Today"
    ],
    "ORG": [
      "Champlain Housing Trust",
      "Vermont Rental Vouchers",
      "the Coronavirus Relief Fund",
      "Downstreet Housing and Community Development",
      "the Agency of Human Services"
    ],
    "ORDINAL": [
      "first"
    ],
    "PERSON": [
      "Eileen Peltier",
      "Brenda Torpy",
      "Nancy Owens",
      "Elizabeth Bridgewater",
      "Andrew Winter",
      "Windham",
      "Twin Pines Housing"
    ]
  },
  {
    "id": "e1410f9c-99a1-473c-83c3-fccb3b3b2ab2",
    "FAC": [
      "the Gaylord Area Convention and Tourism Bureau"
    ],
    "GPE": [
      "the United States",
      "Gaylord"
    ],
    "NORP": [
      "Zoom"
    ],
    "CARDINAL": [
      "One"
    ],
    "ORG": [
      "the Gaylord tourism bureau",
      "Gaylord"
    ],
    "DATE": [
      "the past few years"
    ]
  },
  {
    "id": "af8903b0-7658-4461-a770-960dbab328f0",
    "GPE": [
      "Harnett County",
      "Lillington",
      "N.C.",
      "Shawtown",
      "LILLINGTON"
    ],
    "CARDINAL": [
      "at least one",
      "One",
      "15",
      "one"
    ],
    "DATE": [
      "31",
      "Saturday"
    ],
    "TIME": [
      "at least 7:15 p.m.",
      "4:05 p.m.",
      "afternoon"
    ],
    "PERSON": [
      "Wayne Coats",
      "Coats",
      "Montice Williams"
    ],
    "ORG": [
      "Deputies",
      "Benson"
    ]
  },
  {
    "id": "ca53af4f-991f-4712-81e0-ddd1591b1705",
    "CARDINAL": [
      "three",
      "13"
    ],
    "PERSON": [
      "Egbert",
      "Michael Egbert"
    ],
    "GPE": [
      "Decatur County",
      "Iowa",
      "Texas",
      "Vietnam"
    ],
    "ORG": [
      "Marine",
      "the U.S. Navy",
      "the Houston Police Department"
    ],
    "DATE": [
      "13 months",
      "1967",
      "2006"
    ]
  },
  {
    "id": "79415524-ac65-4cee-99b7-18fc7265a0be",
    "GPE": [
      "Denver",
      "Larimer County",
      "Douglas county",
      "Larimer",
      "Douglas County's",
      "Colorado",
      "Teller County",
      "Memorial Day",
      "Douglas County",
      "Eagle County"
    ],
    "DATE": [
      "Saturday",
      "summer",
      "Friday",
      "two weeks",
      "3-day"
    ],
    "ORG": [
      "Teller",
      "the Colorado Department of Public and Environment",
      "TCHD",
      "Park Meadows",
      "the Colorado Department of Public Health and Environment",
      "Eagle",
      "The Board of Douglas County Commissioners"
    ],
    "PERSON": [
      "Jared Polis",
      "Roger Partridge",
      "Douglas",
      "Jill Hunsaker Ryan",
      "Ryan",
      "Safer"
    ],
    "CARDINAL": [
      "100,000",
      "21",
      "1,327",
      "one",
      "Nearly 24,000",
      "more than 100",
      "175",
      "two",
      "up to 50"
    ],
    "FAC": [
      "Colorado \\-"
    ],
    "LOC": [
      "the Botanic Gardens"
    ],
    "PERCENT": [
      "20%",
      "50%"
    ],
    "TIME": [
      "24 hours"
    ]
  },
  {
    "id": "ddb781fd-762a-4a61-9969-cac261425f63",
    "ORG": [
      "The Department of Correctional Services",
      "a Department of Correctional Services 2014",
      "Department of Corrections",
      "the Nebraska State Penitentiary",
      "Frakes",
      "Legislature",
      "Nebraska",
      "the Department of Corrections",
      "Lincoln",
      "the Community Corrections Center-Lincoln",
      "the Nebraska State Penitentiary \\-",
      "The Tecumseh State Correctional Institution",
      "ACLU",
      "Lathrop",
      "the Legislature's Judiciary Committee",
      "the Lincoln Correctional Center-Diagnostic and Evaluation Center",
      "Omaha"
    ],
    "DATE": [
      "February",
      "the past several years",
      "next week",
      "March",
      "next year",
      "the end of April",
      "This year",
      "2015",
      "four to five years",
      "the next 100 years",
      "May 1",
      "4201 S. 14th",
      "2022",
      "July 1"
    ],
    "PERSON": [
      "Scott Frakes",
      "Frakes",
      "Lincoln",
      "LB916",
      "Steve Lathrop"
    ],
    "GPE": [
      "St.",
      "Omaha"
    ],
    "CARDINAL": [
      "3,200",
      "more than 800",
      "1,362",
      "200",
      "Three",
      "384",
      "1,038",
      "about 5,430",
      "100",
      "507",
      "409",
      "300",
      "hundreds",
      "two",
      "3300",
      "about 2,200",
      "2700"
    ],
    "MONEY": [
      "$6.1 million",
      "$23.3 million",
      "$5 million",
      "$29.8 million",
      "$52 million",
      "$1.2 million",
      "$200 million"
    ],
    "QUANTITY": [
      "400 acres"
    ],
    "LOC": [
      "Southwest 40th Street",
      "West Claire Avenue",
      "West Van Dorn"
    ],
    "FAC": [
      "South Coddington Avenue",
      "the Nebraska State Penitentiary"
    ],
    "PERCENT": [
      "around 158%",
      "140%"
    ]
  },
  {
    "id": "bda70352-5984-46a9-a891-119037c9c63d",
    "GPE": [
      "Mich.",
      "CASSOPOLIS",
      "Michiana",
      "Calcium",
      "Edwardsburg",
      "New York",
      "Gouverneur",
      "Cassopolis"
    ],
    "PERSON": [
      "Matthew",
      "Robert D.",
      "Randy Scott Repczynski",
      "Gloria Jean",
      "Paul E. Mayhew",
      "Laura",
      "Frederick Robert Finley Sr.",
      "Scott Scheel",
      "William",
      "Matthew Robert Finley",
      "Robert Dick"
    ],
    "DATE": [
      "52",
      "the past several years",
      "May 15, 2020",
      "Sept 16, 1967",
      "May 29"
    ],
    "ORG": [
      "Sawyer) Finley",
      "Mercury Displacement Industries Inc.",
      "the Edwardsburg Presbyterian Church"
    ],
    "CARDINAL": [
      "two"
    ],
    "PRODUCT": [
      "Family"
    ],
    "TIME": [
      "2 p.m."
    ],
    "FAC": [
      "Dailey Road and Dunning Street"
    ]
  },
  {
    "id": "2ae29870-e433-4757-a94d-c495690238f5",
    "ORG": [
      "Myrtle Beach",
      "WBTW",
      "News13",
      "The South Carolina Department of Employment and Workforce",
      "DEW"
    ],
    "CARDINAL": [
      "one",
      "around 200,000"
    ],
    "PERSON": [
      "Timmerson",
      "Legal Officer",
      "Rip Tydz",
      "Todd Timmerson",
      "Brian Gregory"
    ],
    "DATE": [
      "Tuesday",
      "winter"
    ],
    "FAC": [
      "Ocean Boulevard"
    ],
    "PRODUCT": [
      "SC Works"
    ]
  },
  {
    "id": "ff516124-45e4-460d-b6d9-48fad5f25c62",
    "GPE": [
      "New York City",
      "Washington",
      "St. Louis",
      "Philadelphia",
      "Detroit",
      "Manhattan",
      "New York",
      "D.C.",
      "Baltimore",
      "Brooklyn"
    ],
    "PERCENT": [
      "43%",
      "only 1%",
      "100%",
      "only 17%",
      "1%",
      "90%",
      "24%",
      "51%",
      "only 39%",
      "Thirty percent",
      "23% and 6%",
      "only 15%",
      "about 70%",
      "36%",
      "70%",
      "11%",
      "less than 10%"
    ],
    "DATE": [
      "2016-17",
      "November 2017",
      "12 years",
      "2016",
      "more than 90 days",
      "more than three months",
      "2017"
    ],
    "CARDINAL": [
      "five",
      "tens of thousands",
      "13",
      "six",
      "only one",
      "189",
      "half",
      "hundreds",
      "One",
      "2017",
      "Over 100,000"
    ],
    "NORP": [
      "English",
      "Hispanics"
    ],
    "ORG": [
      "the New York State English Language Arts Test",
      "KIPP Infinity Middle School",
      "the Crown Heights Success Academy",
      "Ballou High School's",
      "Ballou High School",
      "D.C. Five percent",
      "Success Academy",
      "Ballou",
      "Success Academy's",
      "William Floyd Elementary School",
      "The New York Times"
    ],
    "PERSON": [
      "William Floyd",
      "Bill de Blasio's",
      "Thomas Sowell",
      "Sowell"
    ],
    "ORDINAL": [
      "fourth",
      "third"
    ],
    "LANGUAGE": [
      "English"
    ]
  },
  {
    "id": "2f872a57-25f2-45ea-ab4c-f02bf10c904c",
    "ORG": [
      "Operationally, Van Son",
      "the Summer Youth Employment Program",
      "a Job Development Bureau",
      "Ways & Means Committee",
      "the Genesee County Job Development Bureau",
      "the bureau for more than 35 years",
      "Legislature Chair Rochelle Stein",
      "The Genesee County Job Development Bureau",
      "Job Development Bureau",
      "Department of Labor",
      "E. Main St.",
      "Committee",
      "the Department of Social Services"
    ],
    "WORK_OF_ART": [
      "World Wide Web"
    ],
    "CARDINAL": [
      "five",
      "587",
      "one",
      "50",
      "100",
      "585",
      "two"
    ],
    "PERSON": [
      "Marianne Clattenburg",
      "Van Son",
      "WIOA",
      "Aldi",
      "Mary Spaulding",
      "Teresa Van Son",
      "Veronica Frost"
    ],
    "DATE": [
      "this year",
      "one-year",
      "at least another year",
      "summer",
      "monthly",
      "earlier this week",
      "344-2042",
      "Jan. 31, 2021",
      "the next month"
    ],
    "GPE": [
      "Genesee County",
      "Livingston County",
      "Clattenburg"
    ],
    "FAC": [
      "the Eastown Plaza"
    ],
    "LAW": [
      "the Workforce Innovation Opportunity Act"
    ],
    "MONEY": [
      "243,800",
      "an additional $23,000"
    ],
    "PERCENT": [
      "over 65 percent"
    ]
  },
  {
    "id": "5eceab7f-f37e-44f4-aba1-19ad9b10f8da",
    "ORG": [
      "the Hesperia City Council",
      "Council",
      "the City Council",
      "HESPERIA",
      "the Police Multiple Response Program",
      "the Daily Press",
      "the Sheriff's Department"
    ],
    "PERSON": [
      "Gregg Wielenga",
      "Bill Holland",
      "Rene Ray De La Cruz",
      "Larry Bird",
      "Brigit Bennington",
      "Rachel Molina"
    ],
    "DATE": [
      "the Fourth of July weekend",
      "the same day",
      "Tuesday",
      "May 19",
      "2016",
      "recent years"
    ],
    "MONEY": [
      "500",
      "1,250",
      "2,000",
      "3,000",
      "up to $1,000",
      "1,000"
    ],
    "ORDINAL": [
      "second",
      "first",
      "third"
    ],
    "GPE": [
      "City",
      "the San Bernardino County",
      "Nevada",
      "Holland",
      "Hesperia",
      "San Bernardino County Sheriff's"
    ],
    "TIME": [
      "every night"
    ],
    "CARDINAL": [
      "760"
    ]
  },
  {
    "id": "d5d89205-adb4-4139-8bf9-e958674a0da7",
    "DATE": [
      "March",
      "Friday",
      "weeks",
      "Thursday",
      "each day",
      "Less than two days",
      "this holiday weekend"
    ],
    "GPE": [
      "New York City",
      "New York's",
      "U.S.",
      "New York",
      "Memorial Day"
    ],
    "CARDINAL": [
      "10",
      "more than 350,000",
      "up to 10",
      "one"
    ],
    "PERSON": [
      "Cuomo",
      "Dunn",
      "Trump",
      "Christopher Dunn",
      "Andrew Cuomo"
    ],
    "ORG": [
      "Copyright 2020 NPR",
      "the New York Civil Liberties Union",
      "the New York City Council's",
      "Councilman Mark D. Levine"
    ],
    "LAW": [
      "the First Amendment"
    ],
    "TIME": [
      "night",
      "hours later"
    ],
    "ORDINAL": [
      "first"
    ]
  },
  {
    "id": "0d06446d-a8fb-422d-a8a2-8e69c9be04ff",
    "ORG": [
      "The Virginia State Police",
      "The Medical Examiner's",
      "MARTINSVILLE"
    ],
    "GPE": [
      "Virginia",
      "Henry County",
      "Va."
    ],
    "CARDINAL": [
      "three",
      "911"
    ],
    "PERSON": [
      "Pamela Morse",
      "Steve Draper",
      "Martinsville Bulletin",
      "Martinsville",
      "David Lee Morse",
      "Morse"
    ],
    "DATE": [
      "May 13",
      "Wednesday"
    ],
    "NORP": [
      "Roanoke"
    ]
  },
  {
    "id": "f63cea4c-f478-4874-a350-41ec049ba56a",
    "GPE": [
      "North County"
    ],
    "DATE": [
      "Friday",
      "11100",
      "36"
    ],
    "TIME": [
      "morning",
      "11:00 a.m."
    ],
    "PERSON": [
      "Jarvis Childress",
      "Childress"
    ],
    "FAC": [
      "Riaza Square"
    ]
  },
  {
    "id": "58ca5429-675c-442c-98de-ad84fd2cf8c2",
    "GPE": [
      "Victoria County"
    ],
    "ORG": [
      "Ana Luz Rodriguez-VasquezWilliam",
      "Courtney Dawn",
      "Amil Shiraed McPeters"
    ],
    "PERSON": [
      "FrickRoy Garza Jr.",
      "James Galvan",
      "Sarah Michelle Armstrong",
      "Anthony Graham",
      "Lacrisha Ann",
      "Jennifer L. TerryMichael",
      "V. Nguyen"
    ]
  },
  {
    "id": "60405989-66ba-421d-a062-5848eb7b6dc7",
    "CARDINAL": [
      "11"
    ],
    "DATE": [
      "Saturday",
      "Sunday",
      "Tuesday",
      "mid 80s",
      "May 23, 2020"
    ],
    "TIME": [
      "night",
      "the afternoon",
      "early evening",
      "tonight",
      "evening"
    ],
    "QUANTITY": [
      "around 83 degrees",
      "84 degrees",
      "60 degrees",
      "61 degrees"
    ],
    "PERCENT": [
      "40 to 50%"
    ],
    "GPE": [
      "Memorial Day"
    ]
  },
  {
    "id": "97c847ae-5055-41ca-9f86-ea055963f1e7",
    "DATE": [
      "41 years ago",
      "Sunday",
      "weekly",
      "June 22",
      "\\- July 10",
      "June 4",
      "June 5",
      "Last fall",
      "May 26",
      "the past few months",
      "400 years",
      "June 19",
      "June 8",
      "today",
      "Tuesday",
      "at least two weeks",
      "the fifth season",
      "May 24",
      "June 11",
      "May 28",
      "March",
      "July 7",
      "2018",
      "his 25 years",
      "Friday, May 29",
      "2004"
    ],
    "ORG": [
      "PBS",
      "the 1772 Foundation",
      "the Granville Corner School",
      "the University of Vermont",
      "The St. Johnsbury History and Heritage Center",
      "Bartok",
      "Park McCullough House",
      "The Retreat Farm Inc.",
      "MSA",
      "Fox Hill, Inc.",
      "Montgomery Historical Society for Pratt Hall",
      "The Charlotte Grange",
      "the UVM Department of Music",
      "Bookshops",
      "Fox Hill",
      "Q&A",
      "Morrisville",
      "Stone Valley Arts",
      "Alloy Orchestra",
      "MACC",
      "Starksboro Village Meeting House Society",
      "Phoenix Books",
      "UVM",
      "Miller",
      "Morrisville Alliance for Culture & Commerce",
      "Outdoor Gear Exchange",
      "The Brattleboro Museum & Art Center",
      "Parker",
      "The Fairfield Community Center Association for The Meeting House",
      "VSO",
      "Corner School Resource Center, Inc.",
      "the Preservation Trust of Vermont",
      "SPA",
      "Amber",
      "Studio Place Arts",
      "BMAC",
      "Center for Arts and Learning",
      "Union Church of New Haven Mills",
      "the University of Colorado",
      "Vermont Symphony Orchestra",
      "The 1772 Foundation"
    ],
    "PERSON": [
      "Copland",
      "Sylvia Parker",
      "Francis Legge",
      "Amber Live",
      "YouTube",
      "Bela Bartok's",
      "Sugar",
      "Rimsky-Korsakov's",
      "Zoom",
      "Graham",
      "Morrisville",
      "Miller",
      "Roger Ebert",
      "Shakespeare",
      "Parker",
      "Worcesters",
      "Brahms",
      "Roger Clark Miller",
      "Amber",
      "Jess Graham's",
      "François Clemmons",
      "Phil Scott",
      "Jane Kittredge"
    ],
    "GPE": [
      "Vermont",
      "the United States",
      "St. Michael's",
      "Rhode Island",
      "Kittredge",
      "Berlin",
      "Burma",
      "North Bennington",
      "Queens",
      "Middlebury",
      "Burlington",
      "Green Dragon",
      "Poultney",
      "Montpelier",
      "Providence",
      "Stowe",
      "Morrisville"
    ],
    "LOC": [
      "Green Mountains"
    ],
    "FAC": [
      "Route 100",
      "Main Street Arts",
      "RIVER - Main Street Arts"
    ],
    "NORP": [
      "Instagram",
      "Scottish",
      "Hungarian"
    ],
    "ORDINAL": [
      "first",
      "tenth"
    ],
    "WORK_OF_ART": [
      "Academic Festival Overture",
      "\"Master Chef\"",
      "Capriccio Espagnol",
      "Mister Rogers' Neighborhood",
      "Peasant Jewels",
      "Officer Clemmons: A Memoir",
      "Shelter in Place",
      "Shelter",
      "Appalachian Spring"
    ],
    "TIME": [
      "4:30 p.m.",
      "2-3 minute",
      "hours",
      "7:30 p.m.",
      "8 p.m."
    ],
    "CARDINAL": [
      "\\-",
      "1:1",
      "11",
      "12",
      "three",
      "Six",
      "802-479-7069",
      "two",
      "6"
    ],
    "PRODUCT": [
      "Session II",
      "Green Zoom Program"
    ],
    "EVENT": [
      "Vermont Shakespeare Festival"
    ],
    "QUANTITY": [
      "a good 12 feet"
    ],
    "MONEY": [
      "100,000",
      "10,000",
      "up to $10,000",
      "5,000"
    ]
  },
  {
    "id": "c637a047-60ff-4cb3-969e-5a0028b45cea",
    "LOC": [
      "Trump",
      "Naples Bay",
      "Southwest Florida"
    ],
    "PRODUCT": [
      "Trump"
    ],
    "ORG": [
      "the Rookery Bay National Estuarine Research Reserve",
      "CNN",
      "Target",
      "the National Cancer Institute",
      "nut",
      "CDC",
      "The U.S. Meat and Poultry Hotline",
      "Naples Daily News",
      "Saturdayand",
      "Rookery Bay Reserve",
      "Healthier",
      "the Republican Club of South Collier County",
      "COVID",
      "the Daily News",
      "The Naples Daily News"
    ],
    "DATE": [
      "two months",
      "Saturday",
      "this Memorial Day weekend",
      "Wednesday",
      "Thursday",
      "the previous day's",
      "many years",
      "every day",
      "March 25, 2017"
    ],
    "CARDINAL": [
      "200 to 300",
      "29",
      "one"
    ],
    "GPE": [
      "Collier County",
      "the United States",
      "Collier County's",
      "Fort Myers Beach",
      "Marco Island",
      "Naples",
      "Lee County",
      "U.S.",
      "Naples City Dock",
      "North Naples",
      "Florida"
    ],
    "PERSON": [
      "Fort Myers",
      "Melanie Chadwick",
      "Jones",
      "Neil LaVince",
      "Editor",
      "Publix",
      "Steve Loyd",
      "Rebekah Jones",
      "Dashboard",
      "Raymond Brooks",
      "E. coli",
      "Dick",
      "Trump",
      "Luke Larson",
      "DeSantis",
      "Isles"
    ],
    "TIME": [
      "10 a.m.",
      "a moment"
    ],
    "FAC": [
      "the Jolley Bridge"
    ],
    "WORK_OF_ART": [
      "the Making Waves for Trump event"
    ],
    "QUANTITY": [
      "at least 6 feet"
    ],
    "NORP": [
      "Trumpian"
    ],
    "ORDINAL": [
      "first"
    ],
    "EVENT": [
      "This Memorial Day weekend"
    ]
  },
  {
    "id": "bd8ad3d7-68ca-4d46-a82b-e1ea096afa26",
    "ORG": [
      "Christian Brothers School",
      "The Advocate and Times-Picayune",
      "NFL",
      "LHSAA",
      "Saints"
    ],
    "CARDINAL": [
      "six"
    ],
    "DATE": [
      "the past 11 weeks",
      "Tulane",
      "30s",
      "40s",
      "the year",
      "50s",
      "weekend"
    ],
    "PERSON": [
      "Doug MoreauTulane",
      "Doug Moreau",
      "Zephyrs",
      "Moreau"
    ],
    "NORP": [
      "Saints",
      "Pelicans"
    ],
    "EVENT": [
      "the Allstate Sugar Bowl"
    ],
    "GPE": [
      "Moreau"
    ]
  },
  {
    "id": "ddc9b34b-3d42-4153-b618-8d0da636c5c6",
    "GPE": [
      "Hong Kong",
      "Monroe County",
      "Jaden",
      "Wuhan",
      "Morgan County",
      "Mooresville",
      "China"
    ],
    "DATE": [
      "the years",
      "1994",
      "recent months",
      "2005",
      "three days",
      "the past week",
      "years"
    ],
    "MONEY": [
      "nearly $20,000",
      "more than $18,000",
      "1000",
      "more than $10,000"
    ],
    "PERSON": [
      "Bing Qiu",
      "Jaden White",
      "Corona",
      "Mooresville High",
      "Qiu"
    ],
    "TIME": [
      "the first 24 hours"
    ],
    "NORP": [
      "Americans",
      "Asian"
    ],
    "CARDINAL": [
      "One",
      "2020",
      "one"
    ],
    "ORG": [
      "GPA",
      "GoFundMe",
      "Mooresville"
    ],
    "WORK_OF_ART": [
      "Today"
    ]
  },
  {
    "id": "6cda90e4-92dc-403b-9515-904ce543b138",
    "PERSON": [
      "Kim L. Cronk",
      "Commissioners",
      "Boar",
      "Fuel Truck"
    ],
    "ORG": [
      "the Indiana Department of Health",
      "The Board of Commissioners",
      "Commissioners",
      "CDC",
      "City Council",
      "II & III",
      "the County Health Department",
      "the County Council and Sheriff",
      "AGE",
      "Gillman's Home Center (",
      "Boars Head & Crown Corporation",
      "Renovation of the W.G. Smith Building",
      "County Council",
      "New Castle Correctional Facility",
      "the Henry County Sheriff's Department",
      "Truck Stop & McDonald's",
      "Crown Corporation"
    ],
    "CARDINAL": [
      "765",
      "two",
      "64",
      "over 1,000"
    ],
    "GPE": [
      "County",
      "New Castle",
      "Henry County Jail",
      "a County Councilman",
      "Henry County"
    ],
    "DATE": [
      "2022",
      "38 years",
      "the past several years",
      "six years"
    ],
    "LOC": [
      "County"
    ]
  },
  {
    "id": "5723d949-29e0-4215-ba56-16f64ed33829",
    "DATE": [
      "2012",
      "nearly four decades",
      "2011",
      "these days",
      "December 2016",
      "More than a decade later",
      "this week",
      "six years",
      "1962"
    ],
    "ORG": [
      "Annie",
      "Connie Schultz",
      "Kent State University's",
      "Annie Glenn",
      "The Plain Dealer",
      "the U.S. Senate",
      "Hollins College",
      "the Annie Glenn",
      "The New York Times",
      "the Annie Glenns"
    ],
    "PERSON": [
      "John Glenn's",
      "John",
      "Sherrod",
      "John Glenn",
      "Sherrod Brown"
    ],
    "CARDINAL": [
      "50s",
      "one"
    ],
    "ORDINAL": [
      "90th",
      "first"
    ],
    "NORP": [
      "Americans",
      "American"
    ],
    "LOC": [
      "earth"
    ],
    "GPE": [
      "America"
    ],
    "WORK_OF_ART": [
      "a Pulitzer Prize"
    ]
  },
  {
    "id": "e11c8456-3a7b-48c8-909f-1a5993b17091",
    "PERSON": [
      "Ashton Hagans \\-",
      "EJ Montgomery",
      "John Calipari",
      "Nick Richards",
      "Immanuel Quickley",
      "Maxey",
      "NABC"
    ],
    "ORG": [
      "NBA",
      "Richards",
      "NCAA",
      "Quickley",
      "Calipari",
      "the NBA Draft"
    ],
    "CARDINAL": [
      "five"
    ],
    "DATE": [
      "later this month",
      "two months",
      "Last week",
      "last year's",
      "May 1",
      "next month's"
    ],
    "GPE": [
      "Kentucky"
    ],
    "NORP": [
      "Hagans",
      "Americans"
    ],
    "ORDINAL": [
      "second",
      "first"
    ],
    "QUANTITY": [
      "six feet"
    ]
  },
  {
    "id": "e3ea4a1c-e43f-4c4b-b491-87bf48adf89f",
    "ORG": [
      "HOLLAND",
      "Tulip Time"
    ],
    "DATE": [
      "this year",
      "annual",
      "2018",
      "each year",
      "late May",
      "two or three years",
      "Each year",
      "next year",
      "March 16",
      "this spring",
      "early June"
    ],
    "GPE": [
      "Michigan",
      "the City of Holland Parks and Recreation Department",
      "Netherlands",
      "Holland",
      "the City of Holland",
      "The City of Holland"
    ],
    "PRODUCT": [
      "Tulip"
    ],
    "FAC": [
      "Windmill Island Gardens",
      "Centennial Park"
    ],
    "PERSON": [
      "Scott",
      "Parks",
      "Jamie Scott"
    ],
    "CARDINAL": [
      "10",
      "300,000-500,000",
      "2020"
    ],
    "MONEY": [
      "$48 million",
      "between 350,000 and 400,000"
    ],
    "EVENT": [
      "Tulip Time 2021",
      "Tulip Time Festival",
      "World War II",
      "festival"
    ],
    "ORDINAL": [
      "first"
    ]
  },
  {
    "id": "1e948691-372e-4860-86e9-9f594ae98918",
    "ORG": [
      "CAIR Oklahoma",
      "EED",
      "Eid ul-Fitr",
      "Eid ul",
      "KFOR"
    ],
    "NORP": [
      "Muslim",
      "Islamic",
      "Muslims",
      "Oklahoma Muslim"
    ],
    "GPE": [
      "Ramadan",
      "Oklahoma"
    ],
    "DATE": [
      "this weekend",
      "this year",
      "the holiday",
      "Sunday",
      "May 24",
      "the month"
    ],
    "PERSON": [
      "Adam Soltani"
    ],
    "WORK_OF_ART": [
      "taqabbalallah ta'atakum"
    ]
  },
  {
    "id": "11bab4cb-310f-43b0-8e0c-51dee6d2aa9f",
    "DATE": [
      "Saturday",
      "the day",
      "today",
      "Sunday",
      "Friday",
      "the start of next week"
    ],
    "TIME": [
      "evening",
      "afternoon"
    ],
    "GPE": [
      "Meriwether Counties",
      "Lee",
      "Clay",
      "east Alabama Counties",
      "Alabama",
      "Memorial Day",
      "Georgia"
    ],
    "PERSON": [
      "Webster"
    ],
    "QUANTITY": [
      "One inch"
    ],
    "ORG": [
      "Barbour Counties"
    ]
  },
  {
    "id": "41e96803-31a4-47bf-9e5b-9af18497f0fb",
    "GPE": [
      "Utah",
      "WEST JORDAN"
    ],
    "CARDINAL": [
      "One",
      "7800",
      "four",
      "one"
    ],
    "TIME": [
      "around 3 a.m.",
      "early Saturday morning"
    ],
    "LOC": [
      "West Jordan"
    ],
    "FAC": [
      "Redwood Road"
    ],
    "ORG": [
      "West Jordan Police"
    ],
    "DATE": [
      "his 20s"
    ],
    "ORDINAL": [
      "second",
      "fourth"
    ]
  },
  {
    "id": "29733af7-66b6-461c-ac93-4cd20ef38ca8",
    "PERSON": [
      "Emiliano Carchia",
      "Nimari Burnett",
      "Olimpia Milano",
      "Jamarius Burton",
      "Kyler Edwards",
      "Jahmi'us Ramsey",
      "Sportando",
      "Kevin McCullar",
      "Edwards",
      "Joel Ntambwe",
      "Tyreek Smith",
      "Ramsey",
      "Duke",
      "Avery Benson",
      "Mac McClung",
      "Misko Raznatovic",
      "Jonathan Kuminga",
      "Milano",
      "Benson",
      "Marcus Santos-Silva",
      "Shannon Jr.",
      "Maestro",
      "Raznatovic"
    ],
    "ORG": [
      "UNLV",
      "Micah Peavy",
      "NCAA",
      "Moretti",
      "Clarendon College",
      "Wichita State",
      "NBA",
      "Clarence Nadolny",
      "NBA Draft",
      "G-League",
      "Texas Tech Athletics",
      "Texas Tech",
      "Prolific Prep Academy",
      "Davide Moretti",
      "Bolgna",
      "Air Force",
      "the Red Raiders",
      "VCU",
      "Red Raider"
    ],
    "DATE": [
      "the last 3 seasons",
      "two-year",
      "the Year",
      "Saturday",
      "2017-18",
      "April 25",
      "a mid-first to second-round pick",
      "Wednesday",
      "last season",
      "May 17",
      "the last six completed seasons",
      "May 18",
      "2020",
      "6-10",
      "multi-year",
      "his senior year",
      "minutes last season"
    ],
    "NORP": [
      "European",
      "Italian"
    ],
    "CARDINAL": [
      "13",
      "one",
      "six",
      "four",
      "1.7",
      "three",
      "2021",
      "seven",
      "28",
      "14",
      "1",
      "1.2",
      "2.3",
      "31",
      "2020",
      "two",
      "6"
    ],
    "ORDINAL": [
      "second",
      "third"
    ],
    "WORK_OF_ART": [
      "Davide Moretti",
      "Chibuzo Agbo"
    ],
    "GPE": [
      "Arlington",
      "Nadolny",
      "San Diego St. Augustine",
      "Georgetown",
      "Kentucky",
      "Duncanville",
      "Napa",
      "Italy",
      "Texas",
      "Milan",
      "McCullar"
    ],
    "LAW": [
      "the Big 12 Freshman",
      "the Big 12 Conference"
    ],
    "PRODUCT": [
      "A.J. Walker",
      "Tournament"
    ],
    "EVENT": [
      "the Italian Cup"
    ],
    "FAC": [
      "Shannon"
    ]
  },
  {
    "id": "f6f391ca-749a-4bfa-9d9c-193104a5d237",
    "ORG": [
      "University of Idaho",
      "Sacred Heart University",
      "Gateway Center at",
      "Wide World of Sports",
      "NBA",
      "the Four Seasons",
      "Colorado College",
      "Wells Fargo Center",
      "Hilton",
      "NHL",
      "Categories  Archives  ",
      "Talking Stick Resort Arena",
      "Disney World",
      "Wayne State University Arena (Pistons G League",
      "NBA Arena Employees",
      "ABC",
      "Seattle NHL Arena",
      "Moody Center (University of Texas",
      "New Los Angeles Clippers Arena",
      "NBA Suspension Expected",
      "Search Arena Digest Archives",
      "Fairfield University Convocation Center",
      "MLS",
      "Legacy Arena",
      "HP Field House",
      "Coronavirus Pandemic Continues",
      "ESPN",
      "Idaho Central Credit Union Arena",
      "the Visa Athletic Center",
      "Disney",
      "ESPN Wide World of Sports"
    ],
    "CARDINAL": [
      "\\-",
      "2009July",
      "2024",
      "2010February",
      "2015September",
      "2009September",
      "2020",
      "2015December",
      "30,000",
      "30",
      "2022",
      "2021",
      "2014December",
      "2017December",
      "2016February 2016January",
      "2016September",
      "2013December",
      "2011September",
      "2012December",
      "2013April"
    ],
    "DATE": [
      "2017July 2017June",
      "2007November",
      "2011May 2011April 2011March",
      "season",
      "2014September 2014August 2014July 2014June",
      "2019July 2019June 2019May",
      "2013July 2013June 2013May",
      "six to eight weeks",
      "2020",
      "2011December 2010November 2010October 2010September",
      "2016August 2016July 2016June 2016May 2016April",
      "2012March 2012February",
      "2018November 2018October",
      "2011June",
      "July 1",
      "2010July 2010June 2010May 2010April",
      "2019",
      "2018June 2018May 2018April 2018March",
      "2008September",
      "2008June",
      "2010December 2009November",
      "6-8 weeks",
      "2015July 2015June 2015May 2015April",
      "June",
      "May 23, 2020",
      "2007",
      "2009June 2009May 2009April",
      "30 Days",
      "2019-2020"
    ],
    "GPE": [
      "New York Islanders",
      "Las Vegas",
      "San Jose",
      "Vegas"
    ],
    "PERSON": [
      "Hockey Arena",
      "Robson Arena",
      "Rupp Arena",
      "Carrier Dome",
      "UD Arena",
      "Kaplan Arena",
      "Mike Bass",
      "Savannah Arena"
    ],
    "ORDINAL": [
      "third"
    ],
    "PERCENT": [
      "100 percent",
      "2012November 2012October"
    ],
    "NORP": [
      "Cuban",
      "Venetian"
    ],
    "TIME": [
      "2009February 2009January",
      "2008October"
    ],
    "FAC": [
      "College Park",
      "Belmont Park Arena"
    ]
  }
]