[{"id": "0000015c-a9f9-4a53-8969-3b1f8a29f9df", "Organization": ["NBA", "Lakers", "league", "Chicago Bulls", "Rockets", "Houston Rockets", "Boston Celtics", "Washington Wizards", "Celtics", "Pistons", "Spurs", "UCLA", "Dream Team"], "Person": ["Michael Jordan", "Magic Johnson", "LeBron James", "Hakeem Olajuwon", "Kareem Abdul-Jabbar", "Shaquille O'Neal", "Kobe Bryant", "Wilt Chamberlain", "Larry Bird", "Bill Russel", "Oscar Robertson", "Robert Horry", "Russel Westbrook", "Babe Ruth", "John Wooden", "Shaq", "Scottie Pippen", "Muhammad Ali", "Ervin"], "JobTitle": ["MVP"], "Sport": ["Basketball"], "Broadcaster": ["ESPN"], "GeographicFeature": ["Mount Rushmore"], "Company": ["Olajuwon"], "Location": ["Chicago", "Miami", "Los Angeles"], "TelevisionShow": ["The Last Dance"], "Quantity": ["50%", "five months", "eight year", "13 years", "10-year", "13-year"]}, {"id": "00007570-107a-45ae-8b81-39d26ec335cb", "Organization": ["Des Plaines American Legion", "Maine East High School", "Legion"], "GeographicFeature": ["Park Ridge"], "Location": ["Des Plaines American", "Rosemont", "Chicago"], "Person": ["Commander Tom Strossner"], "Facility": ["Edward Hotel"], "Quantity": ["52 years"]}, {"id": "0000a58b-9bee-4530-b3de-91c5ad44d0d6", "Location": ["Texas", "Gregg County", "Longview", "Houston"], "Person": ["Mike Morath", "Gov. Greg Abbott", "Betsy DeVos", "Chromebooks"], "Organization": ["Texas school", "TEA", "Texas Education", "U.S. Education"], "Facility": ["Pine Tree ISD"], "JobTitle": ["Commissioner", "Secretary"], "GeographicFeature": ["Spring Hill"], "Quantity": ["$1.29 billion", "$2.09 million", "$81.7 million", "$392 million", "$5 million", "$262,000", "$963,000", "75%", "90%", "5%"]}, {"id": "0000bdfd-7583-403b-9945-07846632e702", "Person": ["Marshal Yanda", "Kevin Dresser", "Jerry Sloan", "Broderson", "Chris Doyle", "Kyle Hendricks", "Jerry Krause", "Stephen Strasburg", "Alan Faneca", "Michael Jordan", "Dennis Rodman", "Isiah Thomas", "Karl Malone", "Luis Castillo", "Phil Jackson", "Chris Paddack", "Tommy", "Julien"], "Location": ["Iowa", "Puerto Vallarta", "Mexico", "Salt Lake City", "Utah"], "Organization": ["Chicago Bulls", "NFL", "NBA", "Baltimore Ravens", "Reds", "Cubs", "Yankees", "ISU", "Davenport Assumption", "Padres", "Cyclones"], "Facility": ["Hilton (Coliseum"], "Quantity": ["184 pounds", "312 pounds", "320 pounds", "45 minutes", "270-pound", "23 years", "86.7 mph", "6-foot"]}, {"id": "00010c62-58cb-4b26-a3ef-3db32b243243", "Person": ["Bonnie Soria Najera", "Rosie Soria", "Leo Soria", "KTSM", "remdesivir"], "Facility": ["Soria family", "Medical Center"], "Location": ["EL PASO", "Texas", "47-years"], "Company": ["El Paso"], "JobTitle": ["Trustee"], "HealthCondition": ["pandemic", "fever"], "Quantity": ["two days", "47-years"]}, {"id": "0001161a-b126-48da-b410-6d01a9028ad4", "Person": ["David", "D.D.", "Janutolo", "E.D."], "Location": ["Johnson City", "GREENEVILLE", "Sullivan County", "Greeneville."], "Company": ["JOHNSON CITY"], "Organization": ["U.S. District Court"], "PrintMedia": ["Kingsport Times News"], "JobTitle": ["Director"], "Quantity": ["10 minutes", "$1.2 million", "five\nminutes", "three\ndays", "$300,000", "$900,000"]}, {"id": "00013410-e210-4ce6-8539-0b20c1f9016b", "Location": ["Montpelier", "Vermont", "Vietnam", "U.S."], "Organization": ["Montpelier City Council", "Vermont Supreme Court"], "Person": ["Sen. George Aiken", "Lyndon Johnson", "Michael Sherman"], "Sport": ["contesting"], "Facility": ["Bashara family"], "JobTitle": ["President"], "Quantity": ["27 feet"]}, {"id": "00017567-3d9d-49fa-bcbf-b9ebcb32a4da", "Location": ["Vermont", "Twin Pines Housing", "Windham"], "Company": ["Downstreet Housing", "Champlain Housing Trust"], "Organization": ["Windsor Housing Trust", "Coronavirus Relief Fund", "Legislature", "legislature", "Agency of Human Services"], "Facility": ["Vermont Rental"], "Person": ["Brenda Torpy", "Andrew Winter", "Peltier", "Nancy Owens", "Elizabeth Bridgewater", "Eileen"], "Quantity": ["$1.25 billion", "$3.5 million", "two months", "$117,000"]}, {"id": "00026d8f-9395-4e62-a58f-0d5b57237f47", "Location": ["Gaylord", "United States"], "Organization": ["Area Convention and Tourism Bureau"], "JobTitle": ["consultant"]}, {"id": "000270f2-5e53-44ce-8dff-5ae9195c3b01", "Location": ["Harnett County", "LILLINGTON", "Shawtown", "N.C."], "Person": ["Sheriff Wayne Coats", "Montice Williams", "Benson"], "Organization": ["WNCN"]}, {"id": "00028dcd-75fd-43fc-97b2-779a03829a4c", "Person": ["Michael Egbert"], "Location": ["Decatur County", "Vietnam", "Texas", "Iowa"], "Organization": ["Houston Police Department", "U.S. Navy", "battalion"], "Quantity": ["13 months"]}, {"id": "0002fbb5-7b56-49c0-8a91-c671453a1db1", "Location": ["Douglas County", "Colorado", "Larimer County", "Denver", "Park Meadows", "Eagle"], "Organization": ["Colorado Department of Public Health and Environment", "Colorado Department of Public"], "Person": ["Jill Hunsaker Ryan", "Douglas", "Teller", "Gov. Jared Polis", "Roger Partridge"], "Facility": ["Botanic Gardens", "Park Meadows"], "JobTitle": ["executivedirector"], "Quantity": ["two weeks", "24 hours", "14-day", "2-week", "3-day", "20%", "50%"]}, {"id": "0002ff67-f882-4cde-8101-367e4740ea5c", "Person": ["Scott Frakes", "Sen. Steve Lathrop", "West Van Dorn"], "Organization": ["Department of Correctional Services", "Nebraska State", "Legislature", "Department of Corrections", "Tecumseh State Correctional Institution", "Community Corrections Center-Lincoln", "ACLU", "Judiciary Committee"], "Location": ["Lincoln", "Omaha", "Nebraska"], "JobTitle": ["Director", "chairman"], "Facility": ["Evaluation Center"], "Quantity": ["$23.3 million", "$29.8 million", "$1.2 million", "$200 million", "$6.1 million", "$52 million", "$5\nmillion", "five years", "100 years", "400 acres", "140%", "158%"]}, {"id": "00033306-0ee7-4eac-b955-77030c430515", "Person": ["Matthew Robert Finley", "Robert Finley Sr.", "Finley Jr.", "Robert Dick", "Scott Scheel", "Randy Scott Repczynski", "Gloria Jean", "Robert D.", "Inurnment", "Frederick", "Family", "William", "Laura"], "Location": ["Edwardsburg", "CASSOPOLIS", "New York", "Dailey", "Gouverneur", "Michiana", "Mich."], "Facility": ["Edwardsburg Presbyterian Church", "Paul E. Mayhew Funeral Home"], "Company": ["Mercury Displacement Industries Inc."]}, {"id": "0003a216-c3bb-4e37-9867-1a2adb77b522", "Person": ["Todd Timmerson", "Brian Gregory"], "Organization": ["South Carolina Department of Employment"], "Location": ["HORRY COUNTY"], "Company": ["Facebook"], "JobTitle": ["SCDEW Chief Legal Officer", "Executive", "General Manager"], "GeographicFeature": ["Myrtle Beach", "Rip Tydz"]}, {"id": "0003db5f-4c92-44d8-9d9b-799845fa6b18", "Organization": ["Ballou High School", "Success Academy", "New York State English", "William Floyd Elementary School", "Crown Heights Success Academy", "Middle School"], "Location": ["New York City", "Baltimore", "Washington", "D.C.", "Philadelphia", "Brooklyn", "Manhattan", "2016-17", "Detroit", "St. Louis"], "Person": ["Dr. Thomas Sowell", "William Floyd", "Ballou", "Mayor Bill de Blasio", "Floyd"], "PrintMedia": ["The New York Times"], "Quantity": ["70%", "1%", "Thirty percent", "Five percent", "three months", "12 years", "90\ndays", "100%", "10%", "11%", "15%", "17%", "23%", "24%", "36%", "39%", "43%", "51%", "90%", "6%"]}, {"id": "00041c8a-b800-4d8a-9680-20f032836708", "Organization": ["Genesee County Job Development Bureau", "Department of Social Services", "Summer Youth Employment Program", "Department of Labor"], "Person": ["Van Son", "Marianne Clattenburg", "Chair Rochelle", "Mary Spaulding", "Teresa", "Veronica Frost", "Stein", "Livingston"], "Location": ["Genesee County"], "JobTitle": ["Job Development Bureau contractor", "director", "team leader"], "Facility": ["Eastown Plaza"], "Company": ["Aldi"], "Quantity": ["one-year", "65 percent", "$243,800", "35 years", "$23,000"]}, {"id": "00048dbb-bf96-4638-9f6c-58da77912af1", "Organization": ["Hesperia City Council", "City Council"], "Location": ["HESPERIA", "San Bernardino County", "Nevada"], "Person": ["Bill Holland", "Deputy City Manager Rachel Molina", "Brigit Bennington", "Rene Ray De La Cruz", "Larry Bird", "Captain Gregg", "Wielenga"], "PrintMedia": ["Daily Press"], "Facility": ["Hesperia Station", "San Bernardino County Fire"], "EmailAddress": ["RDeLaCruz@VVDailyPress.com"], "Quantity": ["$1,000", "$1,250", "$2,000", "$3,000", "$500"], "TwitterHandle": ["@DP_ReneDeLaCruz"]}, {"id": "00049765-bb6b-4380-9740-1e2bc5e628b5", "Location": ["New York City", "U.S."], "Organization": ["New York Civil Liberties Union", "New York City Council"], "JobTitle": ["executive", "chairman", "attorney", "director"], "Person": ["Gov. Andrew Cuomo", "Christopher Dunn", "Councilman Mark D. Levine", "President Trump"], "Company": ["NPR"], "Quantity": ["two days"]}, {"id": "0004e303-8dc0-463a-8f51-a7d15a47d86c", "Person": ["David Lee Morse", "Pamela Morse", "Sheriff Steve Draper"], "Location": ["MARTINSVILLE", "Virginia", "Henry County", "Roanoke", "Va."], "PrintMedia": ["Martinsville Bulletin"], "Crime": ["conspiracy to commit murder", "murder"], "Organization": ["Virginia State Police"], "Quantity": ["63-year", "66-year"]}, {"id": "0004f323-f06a-4465-a1b0-14a671908f54", "Person": ["Jarvis Childress"], "Location": ["North County", "ST. LOUIS"], "Facility": ["Riaza Square"], "Quantity": ["36-year"]}, {"id": "000583a4-5a97-41ed-b293-7d637ca4a91c", "Person": ["Courtney Dawn FrickRoy Garza Jr.", "Jennifer L. TerryMichael James Galvan", "Sarah Michelle Armstrong", "Nga Doan Bich", "Ann MartinTam V. Nguyen", "Amil Shiraed", "Ana Luz", "Anthony Graham", "Lamont Henry"], "Location": ["Victoria County"]}, {"id": "0005fba6-15b9-49ea-9480-d30fbfb47467", "Quantity": ["60 degrees", "61 degrees", "83 degrees", "84 degrees", "50%"]}, {"id": "00062185-cefe-4631-91c0-7a31aedd54c0", "Location": ["Morrisville", "Vermont", "Burlington", "Rhode Island", "North Bennington", "United States", "Middlebury", "Burma", "Providence", "Queens", "www.phoenixbooks.biz"], "Person": ["Roger Clark Miller", "Jess Graham", "Shakespeare", "Sylvia Parker", "Officer Clemmons", "Francis Legge", "Bela Bartok", "Jane Kittredge", "Mister Rogers", "Roger Ebert", "Sylvia Parker retiresBERLIN", "Amber", "LeMay"], "Organization": ["UVM", "Morrisville Alliance for Culture", "BMAC", "MACC", "Preservation Trust of Vermont", "1772 Foundation", "Vermont Symphony Orchestra", "Center for Arts and Learning", "Place Arts", "Alloy Orchestra", "Main Street Arts", "UVM Department of", "Inc.", "University of Colorado"], "Company": ["Facebook", "YouTube", "Phoenix Books", "BMAC"], "JobTitle": ["director", "Master Chef"], "GeographicFeature": ["Green Mountains", "beautiful valley"], "Facility": ["Vermont Shakespeare Festival", "St. Johnsbury History and Heritage Center"]}, {"id": "00062fa7-0854-4b1d-b664-3a586476a911", "PrintMedia": ["Naples Daily News"], "Location": ["Florida", "Naples", "Collier County", "North Naples", "Saturdayand", "United States", "South Collier", "Southwest", "Capri", "Lee County"], "GeographicFeature": ["Rookery Bay Reserve", "Naples Bay"], "Person": ["Rebekah Jones", "Trump", "Steve Loyd", "Luke Larson", "Trumpian", "Melanie Chadwick", "Neil LaVince", "TJ Maxx", "Raymond Brooks", "DeSantis", "burgers", "Dick"], "Organization": ["Rookery Bay National", "Republican Club of", "U.S. Meat and Poultry Hotline", "CDC", "Cancer Institute"], "Facility": ["Estuarine Research Reserve", "Fort Myers Beach", "City Dock", "Jolley Bridge", "Fort Myers"], "Company": ["Publix", "CNN"], "JobTitle": ["President", "Editor"], "HealthCondition": ["salmonella"], "Quantity": ["two months", "6 feet"]}, {"id": "00063891-3970-400e-8a15-9f1f017ab02a", "Person": ["Doug Moreau", "Doug MoreauTulane"], "HealthCondition": ["pandemic", "arthrogryposis multiplexcongenita."], "Organization": ["Tulane", "Saints", "LHSAA", "Christian Brothers School", "NFL"], "Company": ["Allstate"], "Sport": ["football"], "Quantity": ["11 weeks"]}, {"id": "00063c91-929d-4825-b430-34c8da7982e1", "Person": ["Bing Qiu", "Jaden White", "lane"], "Location": ["MOORESVILLE", "Wuhan", "Corona", "China", "Morgan County", "Monroe County"], "Company": ["Hong Kong Restaurant", "Facebook"], "Organization": ["Mooresville High"], "Quantity": ["three days", "24 hours", "$10,000", "$18,000", "$20,000", "$1000"]}, {"id": "00064480-3ffd-40e5-8429-8299d4b6789b", "Location": ["Henry County", "general County", "Indiana"], "Facility": ["Henry County Jail", "New Castle", "New Castle Correctional", "Home Center", "W.G. Smith Building"], "Organization": ["County government", "County Council", "County Health Department", "Board of Commissioners", "Department of Health", "City Council", "Ivy Tech College", "Crown", "Sheriff's Department", "CDC"], "JobTitle": ["County Commissioner", "Commissioner", "engineer", "executive"], "Person": ["Kim L. Cronk", "Gillman"], "Company": ["Crown Corporation", "McDonald"], "Quantity": ["six years", "38 years"]}, {"id": "0006c2fd-d649-486f-9fe6-c4f0d35a32b7", "Person": ["Annie", "Annie Glenn", "John Glenn", "Annie Glenns", "Sherrod Brown", "Connie Schultz", "John"], "Location": ["America"], "Organization": ["U.S. Senate", "Kent State University", "Hollins College", "school of journalism"], "JobTitle": ["senator", "consultant.", "writer"], "PrintMedia": ["The New York Times"], "Company": ["The Plain Dealer"], "EmailAddress": ["schultz.connie@gmail.com"], "Quantity": ["four decades", "100-years", "six years"]}, {"id": "00074a86-0e0b-41a2-adf2-ba266ad88591", "Person": ["John Calipari", "Ashton Hagans", "Nick Richards", "Immanuel Quickley", "EJ Montgomery", "Maxey"], "Organization": ["NBA", "NCAA", "NABC"], "Sport": ["basketball"], "Location": ["LEXINGTON", "Kentucky"], "Quantity": ["two months", "six feet"]}, {"id": "00077393-0823-4022-af9f-5ffb1d155d5c", "Person": ["Jamie Scott", "Parks"], "Location": ["Netherlands", "Holland", "Michigan"], "Company": ["Holland Parks"], "Facility": ["Windmill Island Gardens", "Centennial Park"], "JobTitle": ["Cemetery Deputy Director"], "Organization": ["Recreation Department"], "Quantity": ["$48 million", "three years"]}, {"id": "00078a1c-0772-4a21-8e9e-045d18016014", "Person": ["Eid", "Adam Soltani"], "Location": ["Oklahoma", "OKLAHOMA CITY"], "JobTitle": ["Executive Director of CAIR Oklahoma"], "Organization": ["KFOR", "CAIR"], "HealthCondition": ["pandemic"]}, {"id": "00078de5-ce16-4158-945c-4e620c046298", "Location": ["Meriwether Counties", "Alabama", "Georgia"], "Facility": ["Clay"], "Person": ["Webster", "Barbour", "Lee"], "Quantity": ["One inch"]}, {"id": "00079a72-ad6c-4d26-b49d-ae1eb2f6e2a9", "Facility": ["West Jordan"], "Organization": ["West Jordan Police"], "Location": ["Utah"]}, {"id": "0007c852-6789-4ccc-b507-a6b79d435b9f", "Person": ["Davide Moretti", "Olimpia Milano", "Kyler Edwards", "Misko Raznatovic", "Ramsey", "Emiliano Carchia", "Kevin McCullar", "Terrence Shannon Jr.", "Jonathan Kuminga", "Mac McClung", "Chibuzo Agbo", "Esahia Nyiwe", "Micah Peavy", "Clarence Nadolny", "A.J. Walker", "Joel Ntambwe", "Marcus Santos-Silva", "Smith", "Avery Benson", "Jamarius Burton", "Nimari Burnett", "Tyreek"], "Organization": ["Texas Tech", "Texas Tech Athletics", "NCAA", "NBA", "UNLV", "VCU", "Clarendon College", "Wichita State", "Prolific Prep Academy", "Air Force", "Red Raiders", "Duke"], "Location": ["Texas", "Milan", "Arlington", "Italy", "Auburn", "Duncanville", "2017-18", "San Diego St. Augustine", "Calif", "Napa", "Kentucky"], "Sport": ["basketball"], "Company": ["Sportando"], "Quantity": ["180-pound", "185-pound", "210-pound"]}, {"id": "0007d992-a84d-44f4-b982-6c891557aa56", "Organization": ["NBA", "Wayne State University Arena", "Fairfield University Convocation Center", "Sacred Heart University", "Visa Athletic Center", "Moody Center", "Enterprise Center", "University of Idaho", "New York Islanders", "Colorado College", "NHL"], "Company": ["Disney World", "Disney", "Idaho Central Credit Union Arena", "ABC"], "Facility": ["Savannah Arena", "Kaplan Arena", "UD Arena", "Rupp Arena", "Los Angeles Clippers Arena", "Calgary Flames Arena", "Dickies Arena", "Palm Springs AHL Arena", "Seattle NHL Arena", "UConn Hockey Arena", "Stick Resort Arena", "Liberty Arena", "Legacy Arena", "Belmont Park Arena", "Robson Arena", "Bankers Life Fieldhouse", "Wells Fargo Center", "Chase Center", "HP Field House", "Carrier Dome", "Rocket Mortgage Fieldhouse", "Gateway Center"], "PrintMedia": ["Arena Digest Archives"], "Broadcaster": ["ESPN"], "Location": ["Disney", "Las Vegas", "Vegas", "San Jose", "Coronavirus", "Colisee de Trois-Rivieres"], "Person": ["Mike Bass"], "JobTitle": ["Chief Communications Officer"], "Sport": ["basketball"]}, {"id": "0007de5f-936d-4cc4-8039-993424d2b6b8", "Person": ["Sacia Vanderpool", "Tylor Coley", "Kendall", "Verner Suomi", "Byron", "Ella", "Krystyna Ellew", "Maty Wilke", "Brian", "Heather", "Jonathan Tsipis", "Zach", "Chase"], "Organization": ["UW", "Badgers", "Virginia Commonwealth", "Ivy League", "Engineering Center", "LSU", "Texas Tech"], "Sport": ["basketball", "volleyball", "football"], "Location": ["Minnesota", "Madison", "Utah", "North Dakota", "Northern Colorado", "Kansas", "Wisconsin", "Iowa", "Nebraska"], "JobTitle": ["professor"], "GeographicFeature": ["Beaver Dam"], "Facility": ["Elite Camp"], "Quantity": ["10 months", "6-foot", "43%", "54%", "81%"]}, {"id": "0007e612-95aa-48cf-9c70-0a7144b09cce", "Person": ["Bonnie Soria Najera", "Rosie Soria", "Leo Soria", "KTSM", "remdesivir"], "Facility": ["Soria family", "Medical Center"], "Location": ["EL PASO", "Texas", "47-years"], "Company": ["El Paso"], "JobTitle": ["Trustee"], "HealthCondition": ["pandemic", "fever"], "Quantity": ["two days", "47-years"]}, {"id": "00082744-949c-41a7-8a43-5105635bd588", "Person": ["Rick Rodemacher"], "Location": ["CHESTERFIELD", "Manchester", "Missouri", "Mo."], "Company": ["Dierbergs Markets", "NBC"], "JobTitle": ["director"]}, {"id": "00084d55-6b57-46af-bca2-b92036eabd3e", "JobTitle": ["Reporter"], "Person": ["Amber Rose Isaac", "J. Marion Sims", "Priska Neely", "Julia Simon"], "Location": ["United States", "New York"]}, {"id": "0008df1c-43da-4f1c-b36e-d9fae6de10bd", "Person": ["Conrad Benner", "Jen Devor", "Marian Bailey", "Manuela Guillen", "Martha Rich"], "Location": ["Pennsylvania", "Philadelphia", "Philly"], "Organization": ["legislature"], "Hashtag": ["#VoteByMailPHL"], "Quantity": ["80%"]}, {"id": "0009521d-b5e8-47cc-9e8e-373e13e1ea62", "Person": ["Miles", "Karnes CSL", "H Duvall", "W.D. Burnett", "F. Ruiz", "C.S. Hardwick", "A. Hernandez"], "Company": ["Marathon Oil EF", "Eagle Ford", "Burlington Resources", "Marathon Oil E", "EOG Resources", "Swize McFarland Unit", "Teal Operating", "Devon Energy Production", "Tidal Petroleum"], "Location": ["Karnes City", "Karnes County", "Kenedy", "Seguin", "Gillett", "DeWitt County", "Austin", "Nordheim", "Falls City", "Yoakum"], "Facility": ["Eagle Ford Shale"], "JobTitle": ["Editor"], "Organization": ["Texas Railroad Commission", "San Christoval Ranch Unit B"], "Vehicle": ["Jordan A"], "Quantity": ["12,000 feet", "439\n\nAcres", "60\n\nAcres", "17,000 feet", "23,000 feet", "10\n\nAcres", "1,005 barrels", "1,100 barrels", "1,536 barrels", "1,948 barrels", "2,166 barrels", "2,295 barrels", "2,333 barrels", "2,345 barrels", "2,408 barrels", "2,465 barrels", "2,528 barrels", "2,634 barrels"]}, {"id": "00095e23-8504-4842-b9c0-6477aa4dcbe7", "Location": ["Madison County", "Wampsville", "N.Y.", "Oneida", "New York"], "Organization": ["Committee Memorial Day Ceremony", "Veterans", "National Anthem"], "Facility": ["Madison County Courthouse", "WAVEM Memorial"], "Person": ["Chairman Becker", "Victor Ramirez", "Don Smith"], "Company": ["Veterans Memorial Corporation", "WAVEM"], "JobTitle": ["Chairman", "president"], "Quantity": ["20 seconds", "6 feet"]}, {"id": "000a1e6d-ef1a-41e6-b325-a14f6ecc5c84", "Organization": ["Mooresville Town Council", "Town Council", "Brooklyn Town Council", "Morgan County Fair Board", "Mooresville Government Center", "Mooresville Consolidated School Corp.", "Fair Board", "Edcuation Center"], "Location": ["MOORESVILLE", "MORGAN COUNTY", "pandemic. Town", "BROOKLYN"], "Facility": ["Morgan County Fairgrounds"], "JobTitle": ["executive"], "Quantity": ["11 W"]}, {"id": "000a220a-4365-4482-acb1-dbbedf1330e9", "Person": ["Shelley Ann Luther", "Gov. Greg Abbott", "Judge Eric Moye", "President Donald Trump", "Shelley", "Warren Norred", "Sen. Ted Cruz", "Tim Georgeff", "Sean Hannity", "Barry", "Kenny Porterfield", "Peter Johnson", "Gov. Dan Patrick", "Jenkins", "Phillip Bradley", "Tim McDonald", "Shelley Byrd", "Sarah Palin"], "Company": ["Facebook", "Trump"], "Location": ["Texas", "Dallas", "America", "Frisco", "DFW", "Frisco", "Houston", "Georgeff", "Rosa Parks", "Denton County", "U.S.", "Dallas County", "Castle Hills"], "Broadcaster": ["Fox News"], "Organization": ["GOP", "Center for Disease Control", "Texas Supreme Court", "NRA", "Saddleback College"], "Sport": ["softball"], "JobTitle": ["representative", "vice president of sales"], "PrintMedia": ["Morning News"], "Facility": ["Sola Salon", "Dallas County Judge Clay", "George Allen Courthouse"]}, {"id": "000a2588-18e2-46ee-81b1-7ffea99f1345", "Location": ["HINDS COUNTY", "Mississippi"], "Organization": ["Hinds County Sheriff's Office", "Mississippi Highway Patrol"]}, {"id": "000a3dd5-d059-4cf0-a887-46d695a9b7a7", "Location": ["opciones como estas"], "Company": ["escuelas", "Eso"], "Organization": ["becas federales Education", "American Federation", "The American Federation for Children"], "Person": ["Es decir", "escuela privada", "de matriculacion", "Ademas", "clases virtuales", "emergencia. Hoy dia", "John Schilling", "empresas", "calidad", "respuestas nuevas", "Asimismo"], "Quantity": ["40%", "64%", "69%"]}, {"id": "000a7580-281f-40bc-9960-0fa6f2c6ac11", "Person": ["Fred Krull", "Joan Piper Krull", "John Swallow", "Brendan"], "Organization": ["Carthage College", "EY", "Leadership Council", "Los Angeles", "PLC", "Illinois University"], "Location": ["Carthage", "Carthage", "Los Angeles", "Kenosha"], "Facility": ["Carthage College", "The Tower Residence Hall"], "JobTitle": ["President", "principal", "fiduciary", "advisory board", "chairman", "professional services"], "Company": ["Ernst & Young"], "Quantity": ["three years", "six years"]}, {"id": "000aa8e1-d320-4bec-9c9c-25682a197fc3", "Person": ["Martina Nkwantah", "John Caouette"], "Facility": ["UMass Lowell"], "Location": ["North Middlesex", "New England"], "Organization": ["North Middlesex Regional", "Hawks", "Patriots"], "Sport": ["weight throw"], "Quantity": ["100-meter", "11 inches", "118 feet", "124 feet"]}, {"id": "000b416e-e67f-4532-b5fb-df793f69d20f", "Person": ["Tina Walls", "Wall"], "Organization": ["Enon community"], "Location": ["CHESTER", "Va."], "Company": ["Facebook"], "Crime": ["theft"], "Quantity": ["three weeks", "two 6-foot"]}]